PW_FT_classification/__init__.py
PW_FT_classification/main.py
PytorchWildlife/__init__.py
PytorchWildlife/data/__init__.py
PytorchWildlife/data/datasets.py
PytorchWildlife/data/transforms.py
PytorchWildlife/models/__init__.py
PytorchWildlife/models/classification/__init__.py
PytorchWildlife/models/classification/base_classifier.py
PytorchWildlife/models/classification/resnet_base/__init__.py
PytorchWildlife/models/classification/resnet_base/amazon.py
PytorchWildlife/models/classification/resnet_base/base_classifier.py
PytorchWildlife/models/classification/resnet_base/custom_weights.py
PytorchWildlife/models/classification/resnet_base/opossum.py
PytorchWildlife/models/classification/resnet_base/serengeti.py
PytorchWildlife/models/classification/timm_base/DFNE.py
PytorchWildlife/models/classification/timm_base/Deepfaune.py
PytorchWildlife/models/classification/timm_base/__init__.py
PytorchWildlife/models/classification/timm_base/base_classifier.py
PytorchWildlife/models/detection/__init__.py
PytorchWildlife/models/detection/base_detector.py
PytorchWildlife/models/detection/herdnet/__init__.py
PytorchWildlife/models/detection/herdnet/dla.py
PytorchWildlife/models/detection/herdnet/herdnet.py
PytorchWildlife/models/detection/herdnet/model.py
PytorchWildlife/models/detection/herdnet/animaloc/__init__.py
PytorchWildlife/models/detection/herdnet/animaloc/data/__init__.py
PytorchWildlife/models/detection/herdnet/animaloc/data/patches.py
PytorchWildlife/models/detection/herdnet/animaloc/data/types.py
PytorchWildlife/models/detection/herdnet/animaloc/eval/__init__.py
PytorchWildlife/models/detection/herdnet/animaloc/eval/lmds.py
PytorchWildlife/models/detection/herdnet/animaloc/eval/stitchers.py
PytorchWildlife/models/detection/rtdetr_apache/__init__.py
PytorchWildlife/models/detection/rtdetr_apache/megadetectorv6_apache.py
PytorchWildlife/models/detection/rtdetr_apache/rtdetr_apache_base.py
PytorchWildlife/models/detection/rtdetr_apache/rtdetrv2_pytorch/__init__.py
pytorchwildlife-1.2.4.2.dist-info/licenses/LICENSE.md
pytorchwildlife-1.2.4.2.dist-info/METADATA
pytorchwildlife-1.2.4.2.dist-info/WHEEL
pytorchwildlife-1.2.4.2.dist-info/top_level.txt
pytorchwildlife-1.2.4.2.dist-info/RECORD
