Metadata-Version: 2.4
Name: PytorchWildlife
Version: 1.2.4.2
Summary: a PyTorch Collaborative Deep Learning Framework for Conservation.
Home-page: https://github.com/microsoft/CameraTraps/
Author: Andres Hernandez, Zhongqi Miao, Daniela Ruiz Lopez, Isai Daniel Chacon Silva
Author-email: v-hernandres@microsoft.com, zhongqimiao@microsoft.com, v-druizlopez@microsoft.com, v-ichaconsil@microsoft.com
License: MIT
Keywords: pytorch_wildlife,pytorch,wildlife,megadetector,conservation,animal,detection,classification
Classifier: Development Status :: 3 - Alpha
Classifier: Intended Audience :: Developers
Classifier: License :: OSI Approved :: MIT License
Classifier: Programming Language :: Python :: 3
Requires-Python: >=3.8
License-File: LICENSE.md
Requires-Dist: torch
Requires-Dist: torchvision
Requires-Dist: torchaudio
Requires-Dist: tqdm
Requires-Dist: Pillow
Requires-Dist: supervision==0.23.0
Requires-Dist: gradio
Requires-Dist: ultralytics
Requires-Dist: chardet
Requires-Dist: wget
Requires-Dist: yolov5
Requires-Dist: setuptools
Requires-Dist: scikit-learn
Requires-Dist: timm
Dynamic: author
Dynamic: author-email
Dynamic: classifier
Dynamic: description
Dynamic: description-content-type
Dynamic: home-page
Dynamic: keywords
Dynamic: license
Dynamic: license-file
Dynamic: requires-dist
Dynamic: requires-python
Dynamic: summary
